pysaby.py
pysaby-0.1.4.dist-info/METADATA
pysaby-0.1.4.dist-info/WHEEL
pysaby-0.1.4.dist-info/licenses/LICENSE
pysaby-0.1.4.dist-info/RECORD
