Metadata-Version: 2.4
Name: pysaby
Version: 0.1.4
Summary: Module for simple work with SABY API.
Project-URL: Repository, https://github.com/SecretDerped/pysaby
Author-email: "Alexandr H." <plazpen@gmail.com>
License-Expression: MIT
License-File: LICENSE
Keywords: saby,sbis,сбис
Classifier: Development Status :: 4 - Beta
Classifier: Programming Language :: Python
Requires-Python: >=3.8
